{"companyName": "UPEXI INC", "formType": "10-K", "companyIndustry": "MEDICINAL CHEMICALS & BOTANICAL PRODUCTS", "companySicCode": "[2833]", "dateFiled": "20220928", "wordCounts": {"10": 64, "k": 25, "1": 209, "upxi_10k": 1, "htm": 1, "form": 30, "xml": 1, "version": 1, "0": 10, "encoding": 1, "utf": 1, "8": 36, "united": 18, "states": 29, "securities": 71, "exchange": 35, "commission": 15, "washington": 2, "c": 12, "20549": 2, "mark": 8, "one": 33, "annual": 36, "report": 28, "pursuant": 43, "section": 38, "13": 19, "15": 43, "act": 59, "1934": 10, "fiscal": 32, "year": 150, "ended": 104, "transition": 6, "period": 50, "___________": 1, "____________": 3, "file": 10, "number": 31, "exact": 1, "name": 11, "registrant": 35, "specified": 3, "charter": 8, "state": 43, "jurisdiction": 5, "incorporation": 5, "organization": 5, "r": 1, "employer": 1, "identification": 3, "address": 7, "principal": 49, "executive": 55, "offices": 5, "zip": 1, "code": 10, "telephone": 1, "including": 65, "area": 1, "registered": 11, "12": 16, "b": 17, "title": 2, "class": 5, "trading": 8, "symbol": 2, "stock": 239, "market": 57, "llc": 101, "g": 3, "none": 9, "indicate": 13, "check": 7, "well": 14, "known": 8, "seasoned": 1, "issuer": 4, "defined": 23, "rule": 10, "405": 5, "yes": 3, "required": 30, "reports": 12, "whether": 26, "filed": 14, "preceding": 3, "months": 15, "shorter": 3, "2": 71, "subject": 35, "filing": 6, "requirements": 30, "last": 10, "90": 5, "days": 14, "submitted": 5, "electronically": 1, "every": 4, "interactive": 40, "data": 28, "regulation": 24, "232": 1, "chapter": 3, "submit": 2, "files": 1, "large": 10, "accelerated": 11, "filer": 9, "non": 68, "smaller": 11, "reporting": 51, "company": 543, "emerging": 25, "growth": 75, "see": 4, "definitions": 1, "12b": 4, "elected": 8, "use": 33, "extended": 1, "complying": 5, "new": 32, "revised": 2, "financial": 207, "accounting": 47, "standards": 8, "provided": 22, "shell": 1, "aggregate": 7, "value": 65, "common": 156, "held": 10, "affiliates": 5, "december": 25, "31": 28, "2021": 217, "business": 161, "day": 21, "recently": 5, "completed": 13, "second": 4, "quarter": 13, "approximately": 16, "based": 93, "upon": 50, "closing": 20, "sale": 21, "price": 64, "nasdaq": 11, "capital": 28, "voting": 7, "equity": 57, "september": 30, "27": 18, "2022": 178, "shares": 161, "par": 7, "001": 9, "per": 70, "share": 74, "outstanding": 46, "documents": 2, "incorporated": 4, "reference": 5, "upexi": 67, "inc": 96, "june": 212, "30": 203, "table": 87, "contents": 73, "part": 24, "item": 48, "4": 88, "1a": 2, "risk": 16, "factors": 18, "11": 16, "1b": 2, "unresolved": 2, "staff": 2, "comments": 2, "22": 10, "properties": 3, "3": 61, "legal": 15, "proceedings": 6, "mine": 2, "safety": 5, "disclosures": 9, "ii": 17, "5": 49, "related": 70, "stockholder": 9, "matters": 6, "purchases": 4, "6": 30, "reserved": 2, "23": 5, "7": 45, "management": 68, "discussion": 6, "analysis": 6, "condition": 38, "results": 79, "operations": 116, "24": 7, "7a": 2, "quantitative": 2, "qualitative": 2, "29": 8, "statements": 102, "supplementary": 2, "f": 40, "9": 19, "changes": 25, "disagreements": 2, "accountants": 3, "disclosure": 23, "9a": 2, "controls": 23, "procedures": 22, "9b": 2, "information": 27, "9c": 2, "regarding": 19, "foreign": 7, "jurisdictions": 9, "prevent": 8, "inspections": 2, "iii": 7, "directors": 58, "officers": 28, "corporate": 27, "governance": 13, "32": 5, "compensation": 65, "37": 2, "security": 11, "ownership": 16, "certain": 35, "beneficial": 17, "owners": 3, "40": 5, "relationships": 13, "transactions": 15, "director": 29, "independence": 5, "42": 3, "14": 9, "accountant": 6, "fees": 18, "services": 37, "iv": 4, "exhibits": 5, "statement": 18, "schedules": 4, "43": 3, "16": 12, "summary": 5, "cautionary": 3, "forward": 13, "looking": 12, "contains": 6, "express": 4, "implied": 2, "within": 24, "meaning": 2, "27a": 1, "1933": 2, "amended": 14, "21e": 1, "involve": 4, "substantial": 12, "risks": 18, "uncertainties": 12, "historical": 10, "fact": 1, "contained": 4, "future": 62, "position": 14, "strategy": 7, "plans": 13, "objectives": 2, "words": 2, "believe": 10, "may": 148, "potentially": 5, "estimate": 5, "continue": 29, "anticipate": 4, "plan": 43, "intend": 4, "expect": 12, "expressions": 1, "similar": 22, "substance": 6, "negative": 8, "thereof": 9, "convey": 1, "uncertainty": 8, "events": 10, "outcomes": 1, "intended": 2, "identify": 2, "predictions": 1, "unknown": 2, "entitled": 5, "cause": 9, "industry": 23, "actual": 15, "levels": 12, "activity": 7, "performance": 21, "achievements": 3, "materially": 12, "different": 8, "expressed": 1, "although": 8, "expectations": 4, "reflected": 6, "reasonable": 7, "cannot": 14, "guarantee": 2, "except": 8, "applicable": 27, "law": 9, "laws": 41, "update": 1, "conform": 1, "general": 14, "overview": 2, "used": 22, "current": 35, "unless": 6, "otherwise": 11, "indicated": 4, "terms": 19, "us": 43, "mean": 1, "multi": 4, "faceted": 4, "brand": 16, "owner": 9, "established": 11, "brands": 39, "health": 16, "wellness": 10, "pet": 10, "beauty": 7, "growing": 13, "markets": 29, "operate": 16, "industries": 13, "high": 15, "trends": 13, "look": 5, "drive": 11, "organic": 7, "focus": 14, "direct": 21, "consumer": 43, "amazon": 20, "scalable": 4, "anticipated": 7, "goal": 6, "accumulate": 8, "build": 10, "significant": 40, "customer": 37, "database": 8, "across": 6, "sell": 17, "key": 15, "gains": 7, "sales": 66, "profits": 4, "additional": 37, "acquire": 15, "profitable": 7, "ecommerce": 13, "businesses": 14, "scale": 6, "quickly": 4, "reduce": 9, "costs": 51, "synergies": 5, "utilize": 6, "house": 7, "saas": 6, "programmatic": 8, "ad": 4, "technology": 12, "help": 7, "achieve": 10, "lower": 7, "cost": 36, "acquisition": 81, "increased": 24, "cross": 6, "selling": 11, "portfolio": 8, "nevada": 26, "corporation": 42, "fourteen": 3, "active": 6, "subsidiaries": 15, "thirteen": 1, "wholly": 10, "owned": 22, "subsidiary": 22, "cygnet": 41, "online": 23, "delaware": 41, "limited": 77, "liability": 96, "majority": 4, "55": 10, "follows": 17, "havz": 8, "steam": 11, "wholesale": 9, "california": 27, "swch": 6, "cresco": 6, "trunano": 19, "labs": 18, "infusionz": 57, "holding": 6, "products": 157, "colorado": 11, "grove": 12, "vitamedica": 37, "enterprise": 4, "property": 27, "assets": 93, "17129": 4, "florida": 25, "offers": 13, "addition": 20, "four": 5, "distribution": 20, "hit": 8, "wonder": 8, "holdings": 19, "vape": 1, "estate": 5, "consolidations": 2, "july": 26, "2020": 67, "noncontrolling": 3, "shareholders": 12, "converted": 17, "761": 1, "261": 1, "representing": 4, "minority": 3, "interest": 94, "holders": 6, "277": 5, "778": 8, "acquisitions": 23, "entered": 37, "agreement": 80, "merger": 4, "members": 18, "sellers": 11, "acquired": 26, "100": 5, "membership": 12, "interests": 14, "august": 30, "asset": 36, "purchase": 82, "assume": 2, "liabilities": 50, "leading": 3, "seller": 17, "supplements": 6, "surgery": 4, "recovery": 3, "skin": 3, "october": 23, "gyprock": 5, "mfa": 8, "corp": 8, "sherwood": 5, "ventures": 5, "texas": 4, "april": 22, "single": 11, "investor": 6, "agreements": 16, "enable": 3, "remaining": 17, "45": 4, "following": 36, "two": 31, "years": 72, "status": 8, "jumpstart": 1, "startups": 1, "jobs": 3, "2012": 1, "shall": 6, "deemed": 15, "earliest": 3, "total": 45, "gross": 11, "revenues": 17, "exceed": 6, "235": 1, "000": 58, "amount": 32, "indexed": 1, "inflation": 1, "reflect": 5, "change": 15, "index": 4, "urban": 1, "consumers": 5, "published": 2, "bureau": 1, "labor": 3, "statistics": 1, "fifth": 1, "anniversary": 1, "first": 15, "effective": 16, "ipo": 1, "registration": 5, "occurred": 7, "date": 57, "previous": 3, "issued": 69, "convertible": 53, "debt": 19, "qualifies": 2, "240": 1, "46": 1, "federal": 42, "regulations": 43, "successor": 2, "thereto": 3, "exempt": 2, "404": 10, "sarbanes": 13, "oxley": 13, "2002": 7, "requires": 11, "issuers": 1, "publish": 1, "concerning": 1, "scope": 4, "adequacy": 2, "internal": 34, "control": 34, "structure": 4, "also": 39, "assess": 7, "effectiveness": 13, "firm": 7, "attest": 1, "assessment": 4, "14a": 5, "require": 16, "shareholder": 4, "approval": 3, "golden": 2, "parachutes": 1, "exemptions": 4, "available": 10, "description": 2, "cash": 91, "flow": 5, "17": 12, "changed": 1, "better": 4, "evolution": 2, "overall": 6, "product": 53, "select": 3, "align": 2, "primarily": 8, "conducts": 2, "throughout": 4, "locations": 4, "usa": 2, "various": 23, "entities": 7, "operates": 16, "location": 16, "clearwater": 7, "driven": 5, "site": 8, "remote": 8, "teams": 4, "supports": 3, "oversight": 4, "finances": 2, "operating": 60, "mainly": 2, "development": 14, "fulfillment": 4, "office": 11, "supported": 2, "positions": 15, "team": 20, "portugal": 2, "south": 2, "full": 16, "gmp": 2, "warehouse": 10, "center": 3, "liquidation": 6, "support": 9, "lucky": 3, "tail": 3, "marketing": 16, "daily": 2, "manufacturing": 17, "centers": 2, "las": 1, "vegas": 1, "supporting": 2, "manufactured": 5, "hemp": 59, "ingredients": 12, "continued": 6, "manage": 6, "moving": 6, "towards": 1, "larger": 2, "opportunities": 12, "investments": 4, "regulated": 4, "u": 22, "food": 15, "drug": 15, "administration": 9, "trade": 11, "department": 1, "agriculture": 2, "usda": 2, "agencies": 8, "individual": 1, "initial": 13, "matter": 2, "distributed": 5, "must": 9, "meet": 8, "agricultural": 2, "improvement": 4, "2018": 13, "farm": 16, "bill": 16, "contain": 4, "delta": 4, "tetraydrocannabidiols": 2, "dry": 3, "weight": 4, "basis": 20, "ensure": 6, "compliance": 19, "provision": 13, "manufactures": 4, "distributes": 2, "simply": 1, "manufacturers": 6, "producers": 1, "duly": 4, "licensed": 3, "consequently": 1, "processes": 4, "develops": 2, "sells": 2, "cbd": 34, "cosmetic": 4, "fdca": 12, "fda": 24, "implementing": 7, "neither": 1, "specific": 11, "provisions": 16, "relate": 1, "adulteration": 2, "labeling": 7, "depending": 3, "marketed": 2, "dietary": 13, "supplement": 10, "permissibility": 1, "containing": 4, "cannabinoids": 8, "remains": 3, "flux": 1, "guidance": 9, "titled": 3, "cannabis": 15, "derived": 16, "cannabidiol": 4, "taken": 9, "prohibited": 5, "ingredient": 4, "beverage": 2, "several": 7, "definition": 7, "found": 5, "201": 2, "ff": 2, "article": 2, "authorized": 9, "investigation": 2, "antibiotic": 2, "biological": 2, "clinical": 6, "investigations": 7, "instituted": 2, "existence": 3, "made": 12, "public": 43, "excluded": 2, "301": 2, "makes": 4, "introduce": 4, "deliver": 4, "commerce": 6, "investigated": 2, "prior": 23, "included": 28, "exclusions": 2, "topical": 2, "long": 17, "comply": 12, "created": 2, "task": 3, "force": 4, "currently": 19, "evaluating": 6, "science": 2, "pathways": 3, "regulating": 2, "additionally": 9, "enacted": 7, "pertaining": 6, "handling": 6, "impact": 30, "important": 1, "note": 73, "regulatory": 20, "example": 3, "cbda": 1, "cbdg": 1, "cbdn": 1, "finally": 1, "agency": 1, "vested": 8, "ensuring": 1, "claims": 11, "truthful": 1, "misleading": 2, "global": 9, "rate": 36, "forecast": 2, "percent": 11, "bringing": 2, "worldwide": 3, "542": 1, "trillion": 2, "shopping": 1, "trend": 1, "expected": 17, "grow": 7, "50": 9, "next": 5, "increase": 33, "whopping": 1, "907": 1, "billion": 5, "2025": 5, "saw": 1, "exponential": 1, "pandemic": 14, "apt": 1, "buy": 2, "go": 1, "stores": 3, "cagr": 1, "dipped": 1, "continues": 1, "steadily": 1, "customers": 34, "methods": 1, "diverse": 3, "largest": 3, "channel": 1, "others": 3, "carving": 1, "big": 3, "chunk": 1, "walmart": 3, "ebay": 1, "etsy": 1, "popping": 1, "able": 15, "navigate": 1, "multiple": 4, "marketplaces": 1, "success": 15, "helps": 5, "reach": 1, "demographics": 1, "buying": 1, "behaviors": 1, "creates": 1, "target": 5, "create": 1, "sold": 17, "take": 12, "advantage": 7, "list": 6, "foremost": 1, "end": 12, "via": 1, "internet": 1, "however": 7, "retail": 5, "cooperatives": 1, "affiliate": 2, "master": 2, "distributors": 26, "develop": 7, "prioritized": 1, "eliminated": 5, "responds": 1, "developments": 2, "competitive": 11, "strengths": 1, "attribute": 2, "diversification": 1, "offerings": 6, "aggregator": 1, "research": 12, "carefully": 2, "tracks": 1, "rates": 4, "serves": 5, "means": 4, "identifying": 2, "many": 6, "companies": 35, "spend": 1, "spent": 1, "profitability": 5, "foundation": 3, "toughest": 1, "times": 5, "remained": 2, "patient": 1, "aggregators": 4, "extending": 1, "favorable": 5, "valuations": 2, "advertising": 19, "understand": 2, "comes": 2, "investment": 11, "lowering": 1, "providing": 6, "revenue": 59, "stream": 2, "outsource": 1, "allows": 6, "launch": 1, "logistical": 1, "expertise": 2, "background": 2, "logistics": 9, "ceo": 8, "allan": 22, "marshall": 38, "founder": 1, "xpo": 4, "formerly": 1, "segmentz": 4, "shipping": 6, "affecting": 7, "retailers": 2, "strength": 1, "understanding": 6, "finding": 2, "ways": 2, "overhead": 1, "thus": 1, "increasing": 2, "profit": 7, "margins": 3, "resellers": 5, "represent": 5, "bulk": 1, "quick": 1, "resale": 1, "listings": 1, "partnerships": 4, "likes": 1, "bj": 2, "costco": 2, "sam": 2, "club": 2, "etc": 1, "expand": 7, "network": 6, "branded": 6, "without": 4, "added": 3, "line": 8, "grown": 2, "box": 2, "order": 10, "place": 5, "longstanding": 1, "accounts": 26, "untapped": 1, "streams": 1, "professionalism": 2, "entrepreneurial": 2, "culture": 2, "foster": 1, "highly": 8, "dedicated": 1, "employees": 27, "provide": 19, "unsurpassed": 1, "service": 12, "invest": 2, "talent": 4, "employee": 10, "extensive": 5, "ongoing": 4, "education": 3, "successfully": 10, "developed": 4, "programs": 8, "comprehensive": 2, "knowledge": 3, "tools": 2, "needed": 3, "unique": 1, "personalities": 1, "decision": 2, "making": 6, "experienced": 3, "proven": 3, "driving": 3, "accretive": 1, "experience": 17, "senior": 7, "brings": 1, "mergers": 1, "packaged": 1, "goods": 13, "third": 10, "party": 15, "expansion": 8, "strategic": 7, "driver": 2, "tap": 1, "stage": 4, "lifecycle": 1, "lack": 2, "resources": 17, "personnel": 7, "rapidly": 6, "model": 3, "inject": 1, "hopes": 1, "efficiently": 2, "liquidators": 1, "major": 1, "realized": 2, "potential": 12, "acquiring": 4, "space": 8, "otc": 1, "letter": 2, "intent": 1, "signed": 4, "e": 9, "core": 10, "segment": 4, "lucrative": 1, "establish": 4, "strong": 1, "process": 5, "evaluate": 8, "responsible": 9, "tough": 1, "hiring": 1, "method": 13, "get": 1, "great": 1, "retain": 13, "often": 2, "heartbeat": 1, "said": 1, "give": 1, "even": 8, "launched": 2, "internally": 2, "strongly": 1, "relies": 1, "experts": 1, "acts": 3, "provides": 7, "endless": 1, "publishers": 1, "advertisers": 1, "monetize": 1, "cpms": 1, "average": 21, "values": 17, "international": 11, "primary": 4, "mentioned": 2, "forecasted": 2, "stronger": 1, "presence": 1, "nearly": 1, "offered": 2, "aggregation": 2, "craze": 1, "took": 1, "2019": 46, "overpaying": 1, "funding": 6, "seek": 3, "opportunity": 4, "bring": 1, "worse": 1, "overwhelmed": 1, "unprepared": 1, "competition": 12, "heavy": 1, "seems": 1, "trying": 1, "carve": 1, "niche": 1, "compete": 15, "national": 7, "substantially": 8, "greater": 9, "competitors": 12, "consist": 6, "funded": 1, "private": 6, "never": 2, "rather": 2, "overextend": 1, "pay": 3, "make": 19, "sense": 1, "government": 5, "areas": 3, "affect": 24, "activities": 25, "nutritional": 2, "protection": 11, "intellectual": 10, "infringement": 4, "import": 1, "export": 2, "healthcare": 1, "environmental": 1, "successful": 4, "execution": 1, "contingent": 4, "obtaining": 3, "necessary": 4, "approvals": 5, "permits": 5, "registrations": 1, "onerous": 1, "expensive": 4, "rise": 1, "result": 26, "less": 16, "attractive": 2, "delay": 6, "introduction": 3, "implement": 4, "policies": 9, "designed": 4, "evolving": 5, "numerous": 8, "packaging": 1, "beverages": 1, "personal": 2, "care": 1, "cosmetics": 1, "like": 4, "regulates": 2, "promulgated": 3, "particular": 5, "letters": 1, "initiated": 4, "bills": 1, "introduced": 3, "senate": 1, "representatives": 1, "proposed": 6, "legislation": 7, "clarify": 1, "generally": 21, "approved": 16, "congress": 3, "president": 9, "rulemaking": 1, "either": 10, "positively": 2, "adversely": 20, "distribute": 1, "outside": 2, "aware": 1, "regard": 3, "flavoring": 1, "user": 1, "europe": 1, "responsibility": 3, "european": 2, "passed": 2, "forms": 3, "governing": 3, "cultivation": 2, "processing": 6, "yet": 3, "near": 3, "specifically": 1, "enacts": 1, "preempting": 1, "presently": 1, "ability": 27, "130": 3, "time": 36, "working": 12, "headquarters": 1, "henderson": 5, "facility": 12, "warehouses": 2, "southern": 1, "los": 1, "angeles": 1, "individuals": 4, "home": 2, "find": 1, "advised": 1, "read": 4, "conjunction": 4, "sec": 20, "obtain": 14, "copies": 1, "directly": 9, "room": 2, "street": 1, "n": 1, "access": 3, "calling": 1, "800": 2, "0330": 1, "maintains": 1, "electronic": 1, "filers": 3, "website": 3, "http": 1, "www": 1, "gov": 1, "investing": 6, "involves": 1, "degree": 3, "consider": 3, "described": 5, "set": 7, "forth": 8, "flows": 19, "prospects": 8, "case": 3, "decline": 2, "lose": 4, "relating": 8, "history": 6, "difficult": 11, "investors": 11, "commenced": 6, "thereafter": 3, "accordingly": 9, "base": 6, "evaluation": 18, "periods": 13, "assure": 3, "sustain": 2, "considered": 6, "light": 3, "encountered": 1, "early": 2, "particularly": 2, "depend": 12, "attracting": 1, "retaining": 1, "motivated": 1, "qualified": 8, "short": 3, "term": 34, "credit": 5, "lines": 5, "financing": 11, "sources": 4, "offering": 15, "economic": 13, "conditions": 18, "assurance": 9, "efforts": 9, "ultimately": 4, "attain": 1, "unable": 10, "protect": 4, "rights": 13, "harmed": 2, "commercial": 1, "maintain": 10, "appropriate": 7, "countries": 2, "respect": 8, "proprietary": 4, "formulations": 1, "depends": 5, "recognition": 10, "using": 8, "trademarks": 2, "marks": 1, "dress": 1, "rely": 2, "secret": 1, "trademark": 1, "patent": 1, "copyright": 1, "confidentiality": 4, "parties": 5, "offer": 2, "steps": 5, "adequate": 4, "preclude": 1, "misappropriation": 2, "unsuccessful": 1, "inadequate": 2, "misappropriates": 1, "infringes": 1, "material": 43, "adverse": 39, "effect": 43, "achieving": 2, "maintaining": 6, "acceptance": 2, "protecting": 1, "unauthorized": 2, "cases": 2, "possible": 9, "impossible": 2, "detect": 3, "proving": 1, "effectively": 9, "need": 4, "managerial": 2, "operational": 3, "expects": 5, "strain": 4, "facilities": 2, "systems": 10, "inability": 3, "timely": 7, "manner": 5, "predict": 6, "expenses": 31, "brief": 2, "equipment": 26, "supplies": 1, "expenditure": 2, "items": 3, "predicted": 2, "likewise": 1, "compensating": 2, "consultants": 9, "higher": 3, "estimates": 17, "lead": 1, "sustained": 2, "losses": 9, "quarterly": 4, "fluctuate": 2, "net": 89, "vary": 1, "significantly": 5, "due": 16, "demand": 7, "existing": 13, "encourage": 3, "repeat": 1, "inventory": 26, "domestically": 1, "creating": 2, "expanding": 1, "variability": 1, "quarters": 2, "stockholders": 13, "preparing": 2, "proxy": 4, "furnishing": 1, "audited": 4, "privately": 1, "consuming": 3, "costly": 3, "hire": 1, "finance": 4, "cybersecurity": 4, "breaches": 2, "degrade": 1, "conduct": 6, "recognize": 5, "compromise": 1, "integrity": 2, "software": 5, "theft": 1, "damage": 1, "reputation": 3, "expose": 5, "incur": 12, "networks": 2, "increasingly": 1, "virtually": 1, "ranging": 2, "communications": 3, "partners": 3, "computer": 3, "programmers": 2, "attempt": 1, "penetrate": 1, "misappropriate": 1, "interruptions": 1, "techniques": 2, "sabotage": 1, "frequently": 1, "recognized": 25, "sophisticated": 2, "hardware": 1, "system": 4, "applications": 2, "produce": 1, "procure": 2, "defects": 1, "design": 4, "manufacture": 7, "bugs": 1, "problems": 1, "unexpectedly": 1, "interfere": 1, "operation": 6, "outsourced": 1, "functions": 2, "contractors": 6, "providers": 2, "measures": 19, "similarly": 2, "integrators": 1, "reliability": 2, "appropriately": 2, "handle": 1, "confidential": 1, "deploy": 1, "safe": 1, "secure": 2, "fashion": 1, "loss": 45, "fail": 9, "cyberattacks": 1, "mishandling": 1, "damaged": 1, "failure": 13, "include": 33, "beginning": 4, "ending": 5, "weaknesses": 1, "identified": 4, "confidence": 2, "covid": 33, "19": 37, "mitigate": 2, "liquidity": 4, "involving": 1, "novel": 3, "coronavirus": 5, "respiratory": 1, "disease": 2, "refer": 1, "combat": 2, "authorities": 7, "governments": 3, "local": 8, "announced": 1, "respond": 6, "indirectly": 3, "voluntary": 2, "mandatory": 2, "quarantines": 1, "restrictions": 4, "travel": 3, "limiting": 3, "gatherings": 1, "people": 1, "places": 1, "undertaken": 1, "effort": 1, "spread": 6, "person": 13, "meetings": 1, "continuity": 2, "requiring": 1, "remotely": 1, "normal": 3, "level": 17, "quality": 4, "notwithstanding": 1, "impacted": 4, "moreover": 1, "previously": 10, "caused": 6, "temporary": 8, "delays": 2, "delivery": 4, "longer": 7, "experiencing": 1, "imposed": 2, "visit": 1, "presentations": 1, "substituted": 1, "conference": 1, "calls": 1, "mitigation": 1, "affected": 5, "resulting": 10, "reduced": 9, "spending": 3, "changing": 6, "know": 1, "localized": 1, "outbreaks": 1, "recurrences": 1, "disrupt": 4, "extent": 7, "disruption": 4, "restart": 1, "effects": 4, "restrictive": 2, "economy": 2, "geographies": 1, "response": 1, "suppliers": 6, "persist": 1, "ease": 1, "negatively": 7, "responses": 1, "prolonged": 1, "downturn": 1, "uncertain": 6, "decreased": 2, "unemployment": 1, "declining": 2, "pose": 1, "challenges": 2, "devote": 2, "unfavorable": 5, "increases": 6, "supply": 9, "shortage": 2, "raw": 17, "materials": 19, "harm": 6, "interruption": 2, "aluminum": 1, "prices": 21, "recoup": 1, "continuing": 4, "listing": 8, "de": 2, "satisfy": 1, "minimum": 8, "bid": 2, "delist": 1, "delisting": 2, "likely": 9, "impair": 2, "wish": 1, "event": 5, "actions": 7, "restore": 1, "action": 4, "allow": 3, "become": 5, "listed": 5, "stabilize": 1, "improve": 2, "dropping": 1, "requirement": 1, "demands": 1, "associated": 11, "rules": 12, "implemented": 1, "adapt": 1, "decrease": 7, "income": 75, "divert": 2, "attention": 3, "concerns": 1, "officer": 57, "insurance": 13, "accept": 3, "policy": 6, "limits": 2, "coverage": 4, "attract": 11, "serve": 2, "board": 56, "eligible": 1, "treated": 1, "auditor": 3, "attestation": 2, "obligations": 13, "periodic": 1, "nonbinding": 1, "advisory": 2, "vote": 7, "parachute": 1, "payments": 22, "selected": 3, "five": 17, "circumstances": 9, "earlier": 7, "exceeds": 6, "700": 2, "million": 7, "issue": 3, "three": 18, "cease": 4, "immediately": 7, "among": 11, "things": 2, "remain": 5, "250": 6, "exceeded": 2, "ordinary": 1, "comparison": 1, "stringent": 2, "timing": 1, "environment": 5, "includes": 17, "producing": 1, "distributing": 1, "consumption": 4, "diversity": 1, "developing": 3, "face": 5, "entrants": 4, "enters": 3, "downward": 1, "pricing": 2, "pressure": 1, "production": 6, "encounter": 1, "difficulties": 3, "generating": 1, "positioning": 1, "publicity": 8, "perception": 3, "fluctuations": 1, "influenced": 1, "scientific": 2, "media": 1, "associate": 3, "question": 1, "benefits": 8, "initially": 1, "received": 18, "favorably": 1, "sustainable": 1, "preferences": 3, "consistent": 1, "generate": 2, "accurately": 1, "react": 1, "opinion": 8, "source": 1, "latest": 1, "turn": 1, "needs": 3, "innovate": 1, "competitively": 1, "sufficient": 3, "volumes": 1, "differentiate": 1, "enhancements": 1, "rendered": 4, "obsolete": 10, "integrate": 3, "complement": 1, "pursuit": 2, "investigating": 1, "pursuing": 3, "suitable": 1, "dilutive": 10, "issuances": 1, "incurrence": 1, "fails": 1, "integrated": 5, "realize": 2, "benefit": 9, "relevant": 4, "consummation": 1, "integration": 2, "complex": 1, "savings": 2, "furthermore": 3, "arrangements": 6, "geographic": 1, "arrangement": 6, "hurt": 1, "universities": 1, "institutions": 3, "organizations": 2, "skilled": 1, "fill": 1, "roles": 2, "fully": 4, "strategies": 4, "shortages": 1, "composed": 1, "pass": 1, "believes": 5, "availability": 3, "permit": 1, "industrial": 11, "normally": 3, "climactic": 1, "insect": 1, "infestations": 1, "manual": 1, "harvesting": 1, "reformulations": 1, "qualification": 1, "repackaging": 1, "reduction": 2, "termination": 6, "contracts": 9, "renegotiation": 2, "supplier": 1, "contract": 10, "limit": 2, "expiration": 2, "put": 4, "disadvantage": 1, "portion": 9, "commitments": 2, "volume": 1, "studies": 2, "plants": 1, "human": 2, "little": 2, "innovative": 1, "combinations": 5, "concentrated": 1, "performs": 3, "tests": 1, "formulation": 1, "ingesting": 2, "instance": 3, "illness": 1, "side": 2, "retailer": 1, "distributor": 1, "manufacturer": 1, "ingested": 1, "inherent": 4, "exposure": 1, "litigation": 4, "alleged": 3, "injury": 1, "contractual": 2, "indemnification": 1, "named": 5, "defendant": 1, "lawsuit": 1, "defendants": 1, "lawsuits": 1, "assertion": 1, "settlement": 7, "uninsured": 1, "claim": 2, "insured": 2, "exceeding": 2, "independent": 35, "productivity": 3, "turnover": 1, "terminate": 1, "channels": 4, "perceptions": 1, "efficacy": 1, "motivation": 1, "training": 3, "numbers": 1, "present": 5, "separate": 2, "apart": 1, "aspects": 1, "interpretation": 3, "treat": 1, "interpretations": 6, "variety": 1, "employers": 1, "employment": 18, "taxes": 23, "penalties": 8, "possibility": 2, "hold": 3, "false": 3, "earnings": 12, "issues": 1, "advertisement": 2, "bans": 1, "subjected": 1, "misrepresentation": 1, "recalls": 2, "relabeling": 1, "18": 10, "arising": 2, "recent": 9, "outbreak": 2, "globe": 1, "impacting": 1, "epidemic": 1, "poses": 1, "prevented": 1, "conducting": 1, "indefinite": 1, "shutdowns": 1, "requested": 1, "mandated": 1, "governmental": 7, "trials": 1, "chain": 1, "shipment": 5, "cyclodextrin": 1, "raise": 1, "disruptions": 3, "consequences": 3, "impacts": 2, "codified": 1, "usc": 5, "1639o": 3, "plant": 9, "sativa": 3, "l": 2, "seeds": 4, "derivatives": 3, "extracts": 1, "isomers": 2, "acids": 1, "salts": 2, "tetrahydrocannabinol": 1, "concentration": 1, "marijuana": 4, "schedule": 8, "controlled": 7, "substances": 6, "21": 16, "802": 2, "parts": 2, "resin": 3, "extracted": 2, "compound": 2, "salt": 2, "derivative": 5, "mixture": 2, "preparation": 8, "mature": 2, "stalks": 3, "fiber": 2, "produced": 1, "oil": 2, "cake": 2, "therefrom": 1, "sterilized": 1, "seed": 1, "incapable": 1, "germination": 1, "meeting": 4, "investigational": 1, "ind": 1, "application": 7, "scheduled": 1, "rigorous": 1, "interaction": 1, "dea": 3, "nida": 1, "institutes": 1, "nih": 1, "therefore": 6, "enforcement": 5, "modify": 2, "released": 2, "noting": 1, "explicitly": 1, "preserved": 1, "authority": 9, "regulate": 1, "compounds": 1, "351": 1, "passage": 2, "constant": 1, "broad": 2, "alter": 1, "violations": 3, "nature": 4, "slow": 6, "dependent": 1, "legislative": 4, "authorization": 2, "amendment": 5, "supplementation": 1, "occurrences": 1, "halt": 1, "progress": 2, "together": 4, "encouraging": 1, "assured": 1, "appears": 1, "ample": 1, "es": 1, "protections": 1, "possessing": 1, "biomass": 3, "lawful": 1, "thc": 3, "finished": 6, "temporarily": 2, "interim": 5, "stages": 2, "occurrence": 3, "variance": 1, "content": 1, "regulators": 1, "violation": 3, "csa": 1, "violate": 2, "commence": 1, "restrict": 1, "adulterated": 1, "misbranded": 1, "ftc": 2, "attorneys": 1, "litigants": 3, "20": 7, "shifting": 1, "necessitates": 1, "building": 5, "robust": 1, "limitation": 1, "civil": 4, "criminal": 3, "damages": 1, "fines": 1, "curtailment": 1, "restructuring": 2, "injunctions": 1, "withdrawals": 1, "seizures": 1, "differing": 1, "opinions": 3, "legislators": 2, "academics": 2, "compliant": 4, "relative": 2, "cultivators": 2, "processors": 2, "engage": 3, "interstate": 2, "landscape": 1, "resolved": 4, "perhaps": 2, "definitive": 2, "judicial": 3, "inconsistent": 1, "licenses": 4, "inhibit": 1, "carry": 1, "internationally": 2, "least": 5, "intends": 1, "imports": 1, "exports": 1, "customs": 1, "importing": 1, "exporting": 1, "varying": 2, "avail": 1, "framework": 3, "histories": 1, "intensify": 1, "given": 4, "rapid": 2, "regional": 1, "economies": 3, "establishing": 2, "marketplace": 1, "keep": 1, "pace": 1, "especially": 1, "pressures": 1, "adequately": 1, "located": 2, "highway": 1, "north": 2, "fl": 3, "33764": 1, "1710": 2, "whitney": 2, "mesa": 3, "nv": 3, "89014": 2, "month": 6, "1051": 1, "mary": 1, "crest": 1, "rd": 1, "suite": 4, "89074": 1, "lease": 60, "expire": 4, "2024": 6, "15000": 1, "avalon": 1, "blvd": 1, "gardena": 1, "ca": 1, "90248": 1, "601": 1, "ave": 1, "209": 1, "210": 2, "delray": 1, "beach": 1, "33445": 1, "2026": 4, "327": 1, "plaza": 1, "real": 5, "2319": 1, "boca": 1, "raton": 1, "33432": 1, "involved": 4, "course": 1, "pending": 2, "proceeding": 5, "best": 3, "contemplating": 1, "reasonably": 5, "traded": 3, "upxi": 1, "sets": 2, "low": 3, "consolidated": 53, "started": 1, "fourth": 2, "99": 2, "36": 6, "93": 1, "84": 1, "86": 1, "79": 2, "81": 1, "thinly": 1, "reported": 18, "quotations": 1, "true": 1, "valuation": 14, "record": 3, "487": 1, "dividend": 6, "dividends": 3, "foreseeable": 1, "determination": 4, "discretion": 8, "instruments": 13, "deems": 1, "sole": 2, "return": 5, "paid": 22, "unregistered": 1, "proceeds": 20, "274": 1, "330": 1, "notes": 56, "automatically": 4, "accrued": 34, "028": 1, "740": 5, "funds": 1, "35": 4, "consulting": 7, "valued": 18, "175": 5, "00": 6, "consultant": 8, "finder": 2, "fee": 3, "completion": 1, "transaction": 20, "515": 2, "82": 1, "306": 2, "945": 2, "764": 1, "876": 2, "75": 1, "666": 3, "667": 6, "subsequently": 7, "clawed": 1, "back": 2, "106": 1, "497": 1, "deficit": 5, "638": 2, "982": 1, "january": 13, "467": 1, "765": 1, "649": 2, "230": 2, "02": 1, "march": 18, "582": 1, "cashless": 5, "exercise": 31, "option": 36, "163": 1, "887": 1, "48": 1, "555": 3, "489": 3, "550": 1, "59": 2, "238": 1, "159": 1, "447": 2, "119": 1, "792": 1, "warrant": 8, "651": 1, "668": 1, "44": 4, "exemption": 1, "506": 3, "thereunder": 4, "corresponding": 9, "elsewhere": 2, "differ": 5, "prepared": 6, "accordance": 15, "principles": 9, "accepted": 7, "america": 5, "gaap": 32, "holds": 3, "controlling": 15, "intercompany": 1, "consolidation": 4, "segments": 1, "organized": 2, "white": 1, "label": 2, "aggregated": 2, "viewed": 1, "reportable": 3, "characteristics": 1, "compared": 11, "herein": 2, "584": 1, "996": 1, "095": 1, "025": 1, "971": 2, "396": 2, "123": 2, "196": 1, "200": 4, "841": 2, "203": 1, "472": 2, "165": 1, "369": 2, "038": 3, "expense": 46, "87": 1, "902": 1, "269": 2, "181": 2, "494": 2, "046": 4, "030": 5, "978": 4, "948": 3, "024": 1, "85": 1, "950": 1, "919": 1, "73": 1, "539": 1, "052": 2, "2023": 11, "managements": 1, "827": 1, "937": 1, "372": 1, "063": 1, "margin": 4, "improved": 3, "56": 3, "49": 3, "58": 1, "purchased": 4, "efficiency": 1, "consolidates": 1, "166": 1, "834": 1, "administrative": 5, "751": 1, "050": 1, "infrastructure": 2, "amortization": 25, "depreciation": 8, "423": 2, "588": 2, "67": 1, "315": 1, "149": 2, "offset": 2, "102": 1, "282": 2, "gain": 16, "forgiveness": 8, "sba": 10, "ppp": 9, "loan": 34, "canceled": 1, "745": 1, "042": 1, "tax": 66, "061": 1, "622": 1, "293": 2, "083": 5, "127": 2, "748": 1, "819": 1, "161": 1, "933": 1, "874": 3, "473": 1, "922": 1, "521": 2, "872": 2, "939": 1, "606": 2, "021": 3, "281": 2, "007": 2, "699": 2, "744": 2, "988": 2, "395": 2, "384": 2, "646": 1, "694": 1, "25": 6, "806": 1, "financed": 1, "629": 1, "153": 1, "deferred": 32, "087": 1, "229": 1, "994": 1, "respectively": 22, "457": 1, "545": 1, "735": 1, "remodel": 1, "741": 2, "62": 3, "122": 2, "422": 1, "129": 1, "678": 2, "975": 1, "888": 3, "repurchase": 3, "002": 1, "repayment": 3, "promissory": 23, "500": 9, "payable": 40, "maturity": 9, "repaid": 9, "becoming": 2, "conversion": 25, "equal": 4, "prospectus": 2, "348": 1, "309": 1, "payment": 20, "loans": 1, "28": 19, "paycheck": 6, "program": 12, "398": 2, "connection": 8, "amounted": 2, "403": 2, "forgiven": 4, "extinguishment": 3, "297": 1, "classified": 4, "balance": 21, "sheet": 10, "300": 7, "995": 2, "150": 2, "small": 4, "fixed": 4, "commencing": 5, "consisting": 5, "731": 1, "monthly": 10, "750": 1, "chief": 43, "080": 1, "bear": 2, "annum": 7, "compounded": 2, "annually": 7, "seventy": 2, "26": 9, "accredited": 2, "receive": 6, "twelve": 5, "original": 11, "holdback": 3, "warrants": 13, "exercisable": 14, "customary": 5, "anti": 2, "dilution": 2, "right": 14, "redeem": 2, "draw": 2, "underwriting": 3, "covenants": 3, "surfaced": 2, "around": 4, "world": 2, "volatility": 4, "breadth": 2, "duration": 3, "combination": 1, "work": 2, "social": 1, "distancing": 1, "minimal": 3, "determine": 3, "expenditures": 2, "critical": 3, "judgments": 2, "amounts": 13, "going": 1, "bad": 4, "debts": 2, "intangible": 19, "assumptions": 10, "believed": 2, "carrying": 12, "discussed": 2, "conformity": 3, "underlying": 7, "allowance": 15, "doubtful": 5, "useful": 5, "lives": 4, "impairment": 25, "lived": 9, "fair": 38, "measured": 3, "transferred": 6, "assumed": 5, "consideration": 21, "attributable": 11, "expensed": 4, "incurred": 6, "excess": 6, "identifiable": 4, "acquiree": 2, "recorded": 22, "goodwill": 22, "evaluates": 6, "simplifying": 2, "test": 7, "triggering": 2, "might": 3, "impaired": 2, "testing": 4, "performed": 5, "comparing": 2, "estimated": 22, "unit": 4, "charge": 4, "analyzes": 2, "orders": 4, "properly": 2, "determining": 5, "fulfills": 2, "licensing": 2, "promised": 4, "distinct": 3, "context": 2, "measurement": 9, "constraint": 2, "variable": 3, "allocation": 5, "v": 2, "satisfies": 2, "obligation": 6, "obligor": 2, "recognizes": 7, "collection": 3, "probable": 2, "domestic": 2, "promotional": 2, "incentives": 4, "allowances": 3, "discounts": 3, "incentivize": 2, "awareness": 4, "point": 4, "ordered": 2, "designated": 2, "collected": 2, "remitted": 2, "accounted": 5, "returns": 11, "pre": 5, "accrue": 2, "records": 3, "advance": 3, "refundable": 3, "billed": 4, "freight": 2, "reviewed": 5, "whenever": 2, "book": 4, "recoverable": 4, "periodically": 2, "indicators": 2, "exist": 2, "undiscounted": 4, "group": 11, "life": 5, "measuring": 5, "grants": 6, "options": 45, "award": 4, "requisite": 2, "usually": 2, "vesting": 12, "vest": 2, "reviews": 2, "show": 1, "slower": 1, "projected": 1, "penetration": 1, "decided": 1, "write": 5, "inventories": 3, "zero": 2, "written": 6, "charges": 2, "adjustments": 7, "reductions": 1, "permanent": 3, "declines": 1, "specialize": 1, "disposed": 2, "unaudited": 8, "reconciliation": 1, "adjusted": 13, "ebitda": 11, "518": 1, "815": 1, "215": 1, "530": 1, "449": 1, "733": 1, "455": 1, "755": 3, "016": 1, "611": 1, "432": 1, "576": 1, "774": 1, "387": 1, "860": 1, "orgiveness": 1, "708": 1, "412": 1, "915": 1, "195": 1, "690": 1, "discloses": 1, "uses": 7, "planning": 3, "purposes": 10, "goals": 2, "measure": 5, "capability": 1, "comparable": 3, "numerical": 1, "excludes": 1, "calculated": 6, "presented": 2, "substitute": 2, "superior": 1, "lieu": 1, "thorough": 1, "reconciliations": 1, "referred": 3, "highlights": 1, "document": 10, "page": 3, "sheets": 3, "accompanying": 6, "collectively": 4, "fairly": 1, "respects": 1, "audits": 5, "pcaob": 4, "conducted": 4, "perform": 2, "audit": 20, "free": 3, "misstatement": 2, "error": 2, "fraud": 4, "engaged": 2, "purpose": 1, "expressing": 1, "performing": 3, "examining": 1, "evidence": 3, "presentation": 4, "served": 9, "since": 4, "id": 1, "consoldiated": 1, "receivable": 10, "prepaid": 5, "receivables": 2, "stockholders'": 4, "contingencies": 1, "preferred": 23, "accumulated": 7, "stockholers'": 1, "integral": 4, "cancelled": 2, "issuance": 24, "series": 2, "basic": 7, "diluted": 9, "weighted": 16, "shareholders'": 1, "reconcile": 1, "offs": 2, "feature": 9, "supplemental": 1, "construction": 1, "warranted": 1, "followed": 1, "equivalents": 4, "considers": 1, "liquid": 1, "maintained": 1, "balances": 3, "federally": 1, "regularly": 1, "worthiness": 1, "attempts": 1, "collect": 1, "failed": 1, "review": 5, "consists": 3, "stated": 3, "realizable": 2, "determined": 11, "obsolescence": 1, "excessive": 2, "deterioration": 1, "straight": 3, "leasehold": 2, "improvements": 2, "amortized": 15, "disposition": 3, "maintenance": 1, "repair": 1, "charged": 1, "resulted": 1, "shown": 3, "loyalty": 3, "points": 3, "accrues": 1, "fulfilling": 1, "redeemed": 1, "reduces": 1, "executed": 2, "continual": 2, "vendors": 2, "asc": 13, "07": 1, "simplifies": 2, "amendments": 2, "specify": 1, "topic": 4, "718": 2, "applies": 2, "grantor": 2, "acquires": 1, "consumed": 1, "issuing": 1, "awards": 11, "whichever": 1, "readily": 1, "determinable": 1, "commitment": 2, "vendor": 2, "reached": 1, "complete": 1, "instrument": 4, "measurements": 2, "fasb": 5, "codification": 2, "820": 5, "defines": 2, "establishes": 2, "expands": 1, "transfer": 2, "exit": 1, "advantageous": 1, "orderly": 1, "participants": 1, "hierarchy": 3, "distinguishes": 1, "participant": 2, "obtained": 1, "observable": 4, "inputs": 7, "entity": 9, "unobservable": 3, "gives": 1, "highest": 1, "priority": 2, "unadjusted": 2, "quoted": 6, "identical": 3, "lowest": 1, "accessible": 2, "unrestricted": 1, "principally": 1, "corroborated": 1, "correlation": 1, "carried": 5, "approximates": 1, "leases": 14, "determines": 1, "inception": 3, "evaluated": 1, "classification": 2, "begins": 1, "commencement": 2, "cancellable": 1, "renewal": 6, "penalty": 2, "renew": 1, "extend": 1, "classifying": 1, "residual": 1, "guarantees": 1, "implicit": 1, "incremental": 5, "borrowing": 3, "discount": 4, "represents": 10, "borrow": 1, "collateralized": 3, "currency": 1, "plus": 4, "differences": 8, "taxable": 7, "deductible": 1, "recovered": 2, "settled": 2, "positive": 2, "identifies": 1, "probability": 1, "upheld": 1, "taxing": 1, "unrecognized": 4, "apply": 1, "enactment": 1, "clarifies": 2, "prescribes": 1, "threshold": 1, "2017": 3, "1986": 1, "reducing": 1, "statutory": 4, "indefinitely": 2, "computed": 2, "dividing": 1, "giving": 3, "issuable": 12, "treasury": 4, "shows": 1, "computation": 1, "numerator": 1, "denominator": 1, "deposits": 5, "pays": 1, "shipped": 2, "deposit": 1, "commissions": 2, "470": 2, "nondetachable": 1, "money": 3, "intrinsic": 3, "offsetting": 1, "exists": 1, "subsequent": 3, "ratio": 2, "trigger": 1, "2007": 1, "810": 2, "65": 1, "parent": 4, "attributed": 2, "attribution": 1, "pronouncements": 3, "asu": 3, "06": 3, "subtopic": 1, "hedging": 1, "removing": 1, "separation": 1, "models": 1, "embedded": 2, "features": 1, "calculating": 2, "adoption": 2, "permitted": 1, "standard": 6, "2016": 1, "edibles": 1, "tinctures": 1, "topicals": 1, "capsules": 1, "specifications": 1, "november": 9, "relations": 3, "final": 5, "former": 1, "february": 15, "222": 3, "acquirer": 4, "101": 10, "389": 1, "932": 1, "400": 4, "respective": 5, "summarizes": 5, "tangible": 4, "expanded": 1, "closed": 1, "david": 2, "rahm": 2, "yvette": 2, "la": 2, "garde": 2, "agreed": 4, "consisted": 4, "close": 2, "negotiable": 5, "favor": 7, "nine": 3, "chairman": 7, "owning": 1, "platform": 1, "placement": 1, "sites": 1, "simple": 1, "dashboard": 1, "restricted": 2, "way": 4, "adjustment": 12, "solicitation": 1, "120": 2, "completes": 1, "calendar": 1, "percentage": 4, "preliminary": 2, "pro": 6, "forma": 6, "combined": 3, "purport": 1, "indicative": 2, "definite": 1, "proforma": 10, "41": 2, "363": 1, "329": 2, "192": 1, "183": 1, "writes": 1, "wrote": 1, "furniture": 1, "fixtures": 1, "vehicles": 2, "disposal": 2, "vender": 2, "names": 1, "2027": 2, "prepayment": 1, "rent": 1, "subscriptions": 1, "leased": 4, "utilities": 2, "repairs": 2, "components": 4, "component": 5, "abandoned": 1, "costa": 1, "negotiated": 1, "assembly": 1, "rou": 1, "reconciles": 1, "displayed": 1, "noncancelable": 1, "imputed": 1, "cards": 1, "seven": 2, "seventeen": 2, "unpaid": 2, "later": 2, "bears": 5, "six": 2, "portions": 2, "qualify": 2, "confirmed": 2, "installment": 1, "thirty": 1, "ucc": 1, "terminated": 3, "unsecured": 1, "pik": 4, "balloon": 1, "deposited": 1, "summarized": 3, "subordinate": 1, "consignment": 1, "60": 8, "gf": 1, "member": 8, "holder": 3, "preferential": 2, "maters": 1, "ten": 7, "votes": 2, "necessarily": 2, "consented": 4, "reverse": 3, "split": 3, "rounded": 1, "nearest": 1, "whole": 1, "registering": 1, "post": 5, "allotment": 1, "underwriter": 5, "therein": 1, "amounting": 1, "underwriters": 1, "deducting": 1, "isolate": 1, "incentive": 10, "persons": 11, "contributions": 4, "reward": 3, "grant": 13, "restructured": 2, "administered": 2, "committee": 46, "appointed": 4, "administer": 2, "interpret": 2, "determinations": 2, "maximum": 3, "transferable": 2, "reflects": 1, "granted": 12, "forfeited": 1, "exercised": 2, "unvested": 1, "black": 2, "scholes": 2, "yield": 1, "curve": 1, "pattern": 1, "charlotte": 2, "web": 2, "cwbhf": 1, "length": 1, "publicly": 2, "similarities": 1, "forfeitures": 4, "partnership": 3, "elections": 2, "taxpaying": 2, "allocable": 2, "paying": 1, "open": 2, "examination": 4, "contributed": 1, "nondeductible": 1, "realization": 1, "carryforwards": 1, "carryforward": 1, "carryover": 1, "statutes": 1, "limitations": 4, "certainty": 1, "indirect": 2, "upp": 3, "apa": 2, "ga": 2, "solutions": 2, "luckytail": 2, "totals": 1, "dollars": 7, "broker": 1, "totaling": 1, "hundred": 6, "thousand": 4, "escrow": 3, "latter": 2, "release": 2, "180": 1, "ninety": 1, "twenty": 1, "492": 1, "supervision": 2, "participation": 3, "13a": 4, "15d": 4, "covered": 2, "concluded": 3, "disclosed": 4, "processed": 2, "communicated": 2, "decisions": 2, "criteria": 4, "sponsoring": 1, "treadway": 1, "coso": 1, "2013": 4, "external": 1, "misstatements": 2, "documentation": 1, "conclusion": 1, "projections": 1, "deteriorate": 1, "proper": 2, "segregation": 1, "duties": 1, "successors": 1, "death": 2, "resignation": 2, "removal": 3, "ages": 1, "age": 1, "robert": 10, "hackett": 10, "andrew": 13, "norstrud": 31, "gene": 13, "salkind": 21, "68": 2, "thomas": 10, "williams": 18, "lawrence": 8, "h": 5, "dugan": 17, "resigned": 4, "account": 1, "past": 5, "indicating": 1, "occupation": 2, "mr": 46, "joined": 3, "retired": 1, "joining": 2, "serial": 1, "entrepreneur": 1, "hyper": 1, "focusing": 1, "behind": 1, "began": 1, "career": 1, "transportation": 4, "founded": 4, "2000": 3, "logistic": 1, "raised": 1, "nyse": 1, "ust": 2, "1995": 2, "whose": 1, "main": 1, "professional": 3, "ceased": 1, "vice": 1, "traffic": 2, "ltd": 1, "canadian": 1, "division": 1, "leasing": 1, "toronto": 1, "ontario": 1, "canada": 1, "j": 6, "became": 1, "worked": 2, "gee": 5, "2014": 2, "2015": 1, "norco": 1, "2011": 2, "2005": 1, "jagged": 2, "peak": 2, "role": 2, "played": 1, "instrumental": 1, "attaining": 1, "initiatives": 1, "completing": 1, "integrating": 1, "thornton": 1, "llp": 2, "pricewaterhousecoopers": 1, "young": 1, "earned": 2, "ba": 1, "western": 1, "college": 1, "emphasis": 1, "university": 7, "certified": 2, "practicing": 1, "neurosurgeon": 1, "philadelphia": 2, "pa": 1, "graduated": 2, "pennsylvania": 4, "1974": 1, "cum": 1, "laude": 1, "medical": 2, "lewis": 2, "katz": 2, "school": 3, "medicine": 3, "1979": 1, "returned": 1, "neurosurgical": 2, "residency": 1, "1985": 1, "resident": 1, "neurosurgery": 3, "hospital": 4, "affiliated": 1, "practice": 1, "neurological": 1, "holy": 1, "redeemer": 1, "albert": 1, "einstein": 1, "jeanes": 1, "authored": 1, "peer": 1, "journal": 1, "articles": 3, "lectures": 1, "country": 1, "topics": 1, "professorships": 1, "allegheny": 1, "33": 1, "dr": 11, "prominent": 1, "pharmaceutical": 1, "arena": 1, "intuitive": 1, "surgical": 1, "pharmacyclics": 1, "grew": 1, "abbvie": 1, "centocor": 1, "nation": 1, "biotechnology": 2, "johnson": 2, "sits": 1, "boards": 1, "cure": 1, "pharmaceuticals": 1, "leader": 2, "field": 1, "redefining": 1, "traditional": 1, "mobiquity": 2, "technologies": 2, "digital": 1, "engagement": 1, "provider": 1, "owns": 3, "mobile": 1, "clients": 1, "execute": 1, "personalized": 1, "experiences": 1, "derm": 1, "tech": 1, "invasive": 1, "dermatological": 1, "molecular": 1, "diagnostics": 1, "bio": 1, "symetrics": 1, "built": 1, "automated": 1, "analytics": 1, "predictive": 1, "modeling": 1, "machine": 1, "learning": 1, "scientists": 1, "biopharma": 1, "discovery": 1, "precision": 1, "leonard": 1, "bruno": 1, "md": 2, "originations": 1, "specialization": 1, "securitization": 1, "mechanisms": 1, "illiquid": 1, "smith": 1, "barney": 1, "ireland": 1, "acting": 1, "wyndham": 1, "bermuda": 1, "captive": 1, "formed": 1, "jtrm": 1, "gih": 1, "arculius": 1, "range": 1, "extension": 9, "workers": 2, "offshore": 1, "union": 1, "intermediary": 1, "facilitated": 1, "trust": 1, "york": 1, "2009": 1, "american": 1, "2008": 1, "chaired": 1, "nominating": 3, "rivers": 1, "water": 1, "farming": 1, "northwestern": 1, "kellogg": 1, "partner": 2, "dorra": 1, "1996": 1, "central": 1, "1989": 1, "family": 3, "34": 1, "involvement": 2, "convicted": 1, "excluding": 2, "minor": 1, "offences": 1, "bankruptcy": 4, "petition": 1, "association": 2, "filings": 4, "petitions": 1, "relief": 1, "court": 3, "district": 1, "managing": 1, "judgment": 3, "decree": 2, "reversed": 4, "suspended": 4, "vacated": 4, "competent": 2, "permanently": 1, "enjoining": 1, "barring": 1, "suspending": 1, "type": 1, "futures": 2, "commodities": 3, "banking": 1, "commodity": 2, "violated": 1, "respecting": 1, "injunction": 1, "disgorgement": 1, "restitution": 1, "desist": 1, "prohibition": 1, "prohibiting": 1, "mail": 1, "wire": 1, "sanction": 1, "self": 1, "78c": 1, "equivalent": 1, "disciplinary": 1, "ethics": 3, "adopted": 6, "exhibit": 8, "s1": 1, "copy": 1, "attached": 1, "waivers": 1, "expert": 2, "5605": 2, "qualifications": 1, "met": 3, "bonus": 8, "reviewing": 3, "entitlement": 1, "approving": 2, "recommending": 3, "advisors": 2, "administering": 1, "engaging": 1, "setting": 1, "counsel": 1, "assessing": 2, "recommendations": 3, "submitting": 1, "recommended": 1, "hereto": 1, "twice": 2, "nomination": 7, "assisting": 1, "proposing": 1, "slate": 1, "nominees": 3, "election": 3, "vacancy": 1, "suitability": 1, "composition": 1, "committees": 1, "monitoring": 3, "aiding": 1, "succession": 1, "guidelines": 1, "nominations": 2, "procedural": 1, "premature": 1, "assistance": 1, "advanced": 1, "candidates": 1, "appointment": 1, "formal": 1, "wishes": 1, "communicate": 1, "directing": 1, "request": 1, "addressed": 1, "appearing": 1, "particulars": 1, "salary": 3, "nonqualified": 2, "840": 2, "096": 1, "977": 1, "003": 1, "284": 1, "615": 1, "910": 1, "026": 1, "525": 1, "325": 1, "600": 2, "625": 1, "476": 1, "956": 1, "344": 1, "900": 2, "644": 1, "184": 1, "198": 2, "383": 1, "070": 1, "125": 2, "913": 2, "_____________": 1, "pension": 3, "retirement": 3, "sharing": 2, "accrual": 3, "486": 1, "72": 1, "692": 1, "owed": 1, "superseded": 1, "automatic": 2, "clause": 2, "notice": 2, "starting": 2, "460": 1, "111": 5, "112": 1, "53": 9, "556": 4, "ratably": 2, "388": 1, "889": 2, "38": 1, "unexercised": 2, "unexercisable": 2, "unearned": 3, "units": 4, "payout": 1, "572": 1, "917": 4, "677": 1, "2031": 9, "833": 1, "333": 20, "2029": 1, "91": 1, "108": 1, "356": 1, "481": 1, "408": 1, "275": 1, "463": 1, "113": 1, "426": 1, "tomas": 1, "39": 2, "exercises": 1, "relieved": 1, "payables": 1, "capacity": 1, "awarded": 1, "indebtedness": 1, "indebted": 1, "713": 1, "345": 1, "shared": 1, "noted": 1, "97": 1, "414": 1, "444": 5, "64": 1, "962": 1, "037": 1, "54": 1, "88": 1, "61": 4, "442": 1, "jeffrey": 1, "bishop": 2, "730": 1, "__________": 1, "13d": 1, "relationship": 1, "power": 7, "dispose": 2, "beneficially": 3, "computing": 1, "reason": 1, "actually": 1, "711": 1, "339": 1, "527": 1, "416": 1, "352": 1, "941": 1, "305": 1, "075": 1, "445": 1, "category": 1, "column": 1, "279": 2, "05": 2, "208": 2, "014": 2, "lesser": 1, "engagements": 1, "160": 1, "114": 1, "137": 1, "63": 1, "981": 2, "420": 1, "177": 1, "approves": 1, "auditors": 3, "unrelated": 1, "compatible": 1, "omitted": 1, "furnished": 2, "herewith": 1, "restated": 2, "255266": 18, "certificate": 2, "40535": 9, "bylaws": 1, "specimen": 1, "jeff": 1, "kyle": 1, "dennis": 1, "jason": 1, "bond": 1, "dated": 21, "bank": 1, "west": 1, "newtek": 1, "representative's": 1, "secured": 1, "011": 1, "eric": 1, "hanig": 1, "x": 14, "certification": 4, "302": 2, "1350": 2, "906": 2, "ins": 1, "inline": 8, "xbrl": 9, "appear": 1, "tags": 1, "sch": 1, "taxonomy": 6, "schema": 1, "cal": 1, "calculation": 1, "linkbase": 4, "def": 1, "lab": 1, "104": 1, "cover": 1, "formatted": 1, "_______": 1, "hereof": 1, "irrespective": 1, "language": 1, "indicates": 1, "compensatory": 1, "signatures": 1, "behalf": 2, "undersigned": 1, "unto": 1, "capacities": 1, "dates": 1, "laurence": 2}, "totalWordsCleaned": 24583, "topWords": {"company": 543, "stock": 239, "2021": 217, "june": 212, "1": 209}, "formUrl": "https://www.sec.gov/Archives/edgar/data/1775194/0001477932-22-007297.txt", "currentDatetime": "20220929-233150"}